oslovision/__init__.py
oslovision/client.py
oslovision-0.1.7.dist-info/LICENSE
oslovision-0.1.7.dist-info/METADATA
oslovision-0.1.7.dist-info/WHEEL
oslovision-0.1.7.dist-info/top_level.txt
oslovision-0.1.7.dist-info/RECORD
