Metadata-Version: 2.1
Name: oslovision
Version: 0.1.7
Summary: Python client for the OsloVision API
Author-email: OsloVision <support@oslo.vision>
License: MIT License
Project-URL: Homepage, https://github.com/oslovision/oslovision-python
Classifier: Programming Language :: Python :: 3
Classifier: License :: OSI Approved :: MIT License
Classifier: Operating System :: OS Independent
Requires-Python: >=3.6
License-File: LICENSE
Requires-Dist: requests>=2.25.0
Provides-Extra: dev
Requires-Dist: pytest>=6.0; extra == "dev"
Requires-Dist: flake8>=3.8; extra == "dev"
Requires-Dist: mypy>=0.800; extra == "dev"
